cosoensis.py
cosoensis-0.9.9.data/scripts/cosoensis
cosoensis-0.9.9.dist-info/COPYING
cosoensis-0.9.9.dist-info/METADATA
cosoensis-0.9.9.dist-info/WHEEL
cosoensis-0.9.9.dist-info/top_level.txt
cosoensis-0.9.9.dist-info/RECORD
